libchecker/__init__.py
pylibchecker-1.0.0.dist-info/LICENSE
pylibchecker-1.0.0.dist-info/METADATA
pylibchecker-1.0.0.dist-info/WHEEL
pylibchecker-1.0.0.dist-info/RECORD
